datasette_parquet/__init__.py
datasette_parquet/ddl.py
datasette_parquet/debounce.py
datasette_parquet/ducky.py
datasette_parquet/exceptions.py
datasette_parquet/patches.py
datasette_parquet/rewrite.py
datasette_parquet/winging_it.py
datasette_parquet-0.6.1.dist-info/COPYING
datasette_parquet-0.6.1.dist-info/LICENSE
datasette_parquet-0.6.1.dist-info/METADATA
datasette_parquet-0.6.1.dist-info/WHEEL
datasette_parquet-0.6.1.dist-info/entry_points.txt
datasette_parquet-0.6.1.dist-info/top_level.txt
datasette_parquet-0.6.1.dist-info/RECORD
