Metadata-Version: 2.1
Name: datasette-parquet
Version: 0.6.1
Summary: Read Parquet files in Datasette
Home-page: https://github.com/cldellow/datasette-parquet
Author: Colin Dellow
License: Apache License, Version 2.0
Project-URL: Issues, https://github.com/cldellow/datasette-parquet/issues
Project-URL: CI, https://github.com/cldellow/datasette-parquet/actions
Project-URL: Changelog, https://github.com/cldellow/datasette-parquet/releases
Classifier: Framework :: Datasette
Classifier: License :: OSI Approved :: Apache Software License
Requires-Python: >=3.7
License-File: LICENSE
License-File: COPYING
Requires-Dist: datasette
Requires-Dist: duckdb
Requires-Dist: sqlglot
Requires-Dist: watchdog
Provides-Extra: test
Requires-Dist: pytest ; extra == 'test'
Requires-Dist: pytest-asyncio ; extra == 'test'
Requires-Dist: pytest-watch ; extra == 'test'
